infpath.py
infpath-1.2.0.dist-info/WHEEL
infpath-1.2.0.dist-info/METADATA
infpath-1.2.0.dist-info/RECORD
