Metadata-Version: 2.1
Name: infpath
Version: 1.2.0
Summary: infpath('PATH', 'OPTION') - For Using.
Author: adamsonScripts
Requires-Python: >=3.6,<4.0
Classifier: Programming Language :: Python :: 3
Classifier: Programming Language :: Python :: 3.10
Classifier: Programming Language :: Python :: 3.6
Classifier: Programming Language :: Python :: 3.7
Classifier: Programming Language :: Python :: 3.8
Classifier: Programming Language :: Python :: 3.9
